genorm
