Metadata-Version: 1.1
Name: genorm
Version: 0.1.23
Summary: GenORM (simple functional MySQL/PostgreSQL ORM)
Home-page: https://bitbucket.org/deniskhodus/genorm
Author: Denis Khodus
Author-email: deniskhodus@gmail.com
License: MIT
Keywords: orm mysql psql postgres postgresql genorm
Platform: UNKNOWN
Classifier: Development Status :: 4 - Beta
Classifier: License :: OSI Approved :: Mozilla Public License 2.0 (MPL 2.0)
Classifier: Programming Language :: Python :: 2
Classifier: Programming Language :: Python :: 3
Classifier: Topic :: Database :: Front-Ends
